LICENSE.md
MANIFEST.in
README.md
TODO.md
pyproject.toml
setup.py
riana/__init__.py
riana/__main__.py
riana/accmass.py
riana/constants.py
riana/logger.py
riana/main.py
riana/models.py
riana/params.py
riana/peptides.py
riana/project.py
riana/riana_fit.py
riana/riana_integrate.py
riana/riana_preprocess.py
riana/spectra.py
riana.egg-info/PKG-INFO
riana.egg-info/SOURCES.txt
riana.egg-info/dependency_links.txt
riana.egg-info/entry_points.txt
riana.egg-info/requires.txt
riana.egg-info/top_level.txt
riana_ui/__init__.py
riana_ui/__main__.py
riana_ui/main.py
riana_ui/riana_ui_integrate.py
riana_ui/riana_ui_model.py
riana_ui/riana_ui_plot.py
riana_ui/test_2_req_args.py
riana_ui/test_3_req_args.py
riana_ui/test_progress_bar.py
tests/__init__.py
tests/test_accmass.py
tests/test_mzml.py
tests/data/.DS_Store
tests/data/sample1/.DS_Store
tests/data/sample1/20180216_BSA.mzML.gz
tests/data/sample1/percolator.target.mzid
tests/data/sample1/percolator.target.psms.txt