Metadata-Version: 2.1
Name: riana
Version: 0.7.2
Summary: riana integrates the relative abundance of isotopomers in mass spectra
Home-page: https://github.com/ed-lau/riana
Author: Edward Lau
Author-email: edward.lau@cuanschutz.edu
Project-URL: Source, https://github.com/ed-lau/riana
Project-URL: Edward Lau Lab, https://www.laulab.net
Keywords: scientific turnover kinetics proteomics mass-spectrometry
Classifier: Development Status :: 4 - Beta
Classifier: Intended Audience :: Developers
Classifier: Topic :: Software Development :: Build Tools
Classifier: License :: OSI Approved :: MIT License
Classifier: Programming Language :: Python :: 3.9
Classifier: Programming Language :: Python :: 3 :: Only
Requires-Python: >=3.9, <4
License-File: LICENSE.md
